netpicker/__init__.py
netpicker/api/__init__.py
netpicker/api/serializers.py
netpicker/api/urls.py
netpicker/api/views.py
netpicker/client.py
netpicker/filtersets.py
netpicker/forms.py
netpicker/migrations/0001_initial.py
netpicker/migrations/0002_mappeddevice_name_netpickerdevice_name.py
netpicker/migrations/0003_rename_setting_netpickersetting.py
netpicker/migrations/__init__.py
netpicker/models/__init__.py
netpicker/models/automation.py
netpicker/models/backup.py
netpicker/models/base.py
netpicker/models/setting.py
netpicker/navigation.py
netpicker/search.py
netpicker/setup/__init__.py
netpicker/setup/__main__.py
netpicker/signals.py
netpicker/static/netpicker/netpicker.svg
netpicker/tables.py
netpicker/templates/netpicker/automation/job-edit.html
netpicker/templates/netpicker/automation/job-logs.html
netpicker/templates/netpicker/automation/job-run.html
netpicker/templates/netpicker/automation/job-view.html
netpicker/templates/netpicker/automation/jobs.html
netpicker/templates/netpicker/automation/log-detail.html
netpicker/templates/netpicker/automation/logs.html
netpicker/templates/netpicker/automation.html
netpicker/templates/netpicker/backup.preview.html
netpicker/templates/netpicker/backup_search.html
netpicker/templates/netpicker/backups.html
netpicker/templates/netpicker/backups_history.html
netpicker/templates/netpicker/buttons/run.html
netpicker/templates/netpicker/devices_list.html
netpicker/templates/netpicker/job.html
netpicker/templates/netpicker/logo.html
netpicker/templates/netpicker/settings/netpicker.html
netpicker/templates/netpicker/settings.html
netpicker/templatetags/__init__.py
netpicker/templatetags/netpicker.py
netpicker/urls.py
netpicker/utilities.py
netpicker/views/__init__.py
netpicker/views/automation.py
netpicker/views/backup.py
netpicker/views/base.py
netpicker/views/devices.py
netpicker/views/setting.py
netpicker_netbox_plugin-0.9.4.dist-info/METADATA
netpicker_netbox_plugin-0.9.4.dist-info/WHEEL
netpicker_netbox_plugin-0.9.4.dist-info/RECORD
