Metadata-Version: 2.4
Name: netpicker-netbox-plugin
Version: 0.9.4
Summary: 
Author: imi
Author-email: isomogyi@hotmail.com
Requires-Python: >=3.11,<4.0
Classifier: Programming Language :: Python :: 3
Classifier: Programming Language :: Python :: 3.11
Classifier: Programming Language :: Python :: 3.12
Classifier: Programming Language :: Python :: 3.13
Classifier: Programming Language :: Python :: 3.14
Requires-Dist: netpicker_client (>=0.4.23.1,<0.5.0.0)
Requires-Dist: pydantic (>=2.11.7,<3.0.0)
